pytdc_nextml-1.2.0.dist-info/licenses/LICENSE
tdc_ml/__init__.py
tdc_ml/base_dataset.py
tdc_ml/evaluator.py
tdc_ml/metadata.py
tdc_ml/version.py
tdc_ml/benchmark_group/__init__.py
tdc_ml/benchmark_group/admet_group.py
tdc_ml/benchmark_group/base_group.py
tdc_ml/benchmark_group/counterfactual_group.py
tdc_ml/benchmark_group/docking_group.py
tdc_ml/benchmark_group/drugcombo_group.py
tdc_ml/benchmark_group/dti_dg_group.py
tdc_ml/benchmark_group/geneperturb_group.py
tdc_ml/benchmark_group/protein_peptide_group.py
tdc_ml/benchmark_group/scdti_group.py
tdc_ml/benchmark_group/tcrepitope_group.py
tdc_ml/chem_utils/__init__.py
tdc_ml/chem_utils/evaluator.py
tdc_ml/chem_utils/featurize/__init__.py
tdc_ml/chem_utils/featurize/_smartsPatts.py
tdc_ml/chem_utils/featurize/_smiles2pubchem.py
tdc_ml/chem_utils/featurize/_xyz2mol.py
tdc_ml/chem_utils/featurize/molconvert.py
tdc_ml/chem_utils/oracle/__init__.py
tdc_ml/chem_utils/oracle/docking.py
tdc_ml/chem_utils/oracle/filter.py
tdc_ml/chem_utils/oracle/oracle.py
tdc_ml/dataset_configs/__init__.py
tdc_ml/dataset_configs/brown_mdm2_ace2_12ca5_config.py
tdc_ml/dataset_configs/config.py
tdc_ml/dataset_configs/config_map.py
tdc_ml/dataset_configs/opentargets_dti.py
tdc_ml/dataset_configs/scperturb_config.py
tdc_ml/feature_generators/__init__.py
tdc_ml/feature_generators/anndata_to_dataframe.py
tdc_ml/feature_generators/base.py
tdc_ml/feature_generators/cellxgene_generator.py
tdc_ml/feature_generators/data_feature_generator.py
tdc_ml/feature_generators/protein_feature_generator.py
tdc_ml/feature_generators/resource.py
tdc_ml/generation/__init__.py
tdc_ml/generation/bi_generation_dataset.py
tdc_ml/generation/generation_dataset.py
tdc_ml/generation/ligandmolgen.py
tdc_ml/generation/molgen.py
tdc_ml/generation/reaction.py
tdc_ml/generation/retrosyn.py
tdc_ml/generation/sbdd.py
tdc_ml/model_server/__init__.py
tdc_ml/model_server/tdc_hf.py
tdc_ml/model_server/model_loaders/__init__.py
tdc_ml/model_server/model_loaders/scvi_loader.py
pytdc_nextml-1.2.0.dist-info/METADATA
pytdc_nextml-1.2.0.dist-info/WHEEL
pytdc_nextml-1.2.0.dist-info/top_level.txt
pytdc_nextml-1.2.0.dist-info/RECORD
