Metadata-Version: 2.4
Name: pytdc-nextml
Version: 1.2.0
Summary: PyTDC: A multimodal machine learning training, evaluation, and inference platform for biomedical foundation models
Home-page: https://github.com/apliko-xyz/PyTDC
Author: PyTDC Team
Author-email: amva13@alum.mit.edu
License: MIT
Requires-Python: >=3.9
License-File: LICENSE
Requires-Dist: accelerate==0.33.0
Requires-Dist: dataclasses<1.0,>=0.6
Requires-Dist: datasets<2.20.0
Requires-Dist: evaluate==0.4.2
Requires-Dist: fuzzywuzzy<1.0,>=0.18.0
Requires-Dist: huggingface_hub<1.0,>=0.34.4
Requires-Dist: numpy<2.0.0,>=1.26.4
Requires-Dist: openpyxl<4.0.0,>=3.0.10
Requires-Dist: pandas<3.0.0,>=2.2.2
Requires-Dist: requests<3.0.0,>=2.31.0
Requires-Dist: scikit-learn>=1.2.2
Requires-Dist: tqdm<5.0.0,>=4.65.0
Requires-Dist: transformers<4.51.0,>=4.43.0
Requires-Dist: gget<1.0.0,>=0.28.4
Requires-Dist: pydantic<3.0.0,>=2.6.3
Requires-Dist: rdkit<2024.3.1,>=2023.9.5
Dynamic: author
Dynamic: author-email
Dynamic: description
Dynamic: description-content-type
Dynamic: home-page
Dynamic: license
Dynamic: license-file
Dynamic: requires-dist
Dynamic: requires-python
Dynamic: summary
